odoo/addons/fieldservice_route_account/README.rst
odoo/addons/fieldservice_route_account/__init__.py
odoo/addons/fieldservice_route_account/__manifest__.py
odoo/addons/fieldservice_route_account/i18n/es_CL.po
odoo/addons/fieldservice_route_account/i18n/fieldservice_route_account.pot
odoo/addons/fieldservice_route_account/i18n/pt_BR.po
odoo/addons/fieldservice_route_account/models/__init__.py
odoo/addons/fieldservice_route_account/models/account_payment.py
odoo/addons/fieldservice_route_account/models/fsm_dayroute_payment.py
odoo/addons/fieldservice_route_account/models/fsm_route_dayroute.py
odoo/addons/fieldservice_route_account/readme/CONTRIBUTORS.rst
odoo/addons/fieldservice_route_account/readme/CREDITS.rst
odoo/addons/fieldservice_route_account/readme/DESCRIPTION.rst
odoo/addons/fieldservice_route_account/readme/USAGE.rst
odoo/addons/fieldservice_route_account/security/ir.model.access.csv
odoo/addons/fieldservice_route_account/static/description/icon.png
odoo/addons/fieldservice_route_account/static/description/index.html
odoo/addons/fieldservice_route_account/tests/__init__.py
odoo/addons/fieldservice_route_account/tests/test_dayroute_payment.py
odoo/addons/fieldservice_route_account/views/fsm_route_dayroute.xml
odoo12_addon_fieldservice_route_account-12.0.1.1.1.dist-info/METADATA
odoo12_addon_fieldservice_route_account-12.0.1.1.1.dist-info/WHEEL
odoo12_addon_fieldservice_route_account-12.0.1.1.1.dist-info/top_level.txt
odoo12_addon_fieldservice_route_account-12.0.1.1.1.dist-info/RECORD
