Metadata-Version: 2.1
Name: odoo12-addon-fieldservice-route-account
Version: 12.0.1.1.1
Summary: Field Service Route Account
Home-page: https://github.com/OCA/field-service
Author: Open Source Integrators, Odoo Community Association (OCA)
Author-email: support@odoo-community.org
License: AGPL-3
Platform: UNKNOWN
Classifier: Programming Language :: Python
Classifier: Framework :: Odoo
Classifier: License :: OSI Approved :: GNU Affero General Public License v3
Classifier: Development Status :: 4 - Beta
Requires-Python: >=3.5
Requires-Dist: odoo12-addon-fieldservice-account-payment
Requires-Dist: odoo12-addon-fieldservice-route
Requires-Dist: odoo (<12.1dev,>=12.0a)
